scubatrace/__init__.py
scubatrace/call.py
scubatrace/clazz.py
scubatrace/file.py
scubatrace/function.py
scubatrace/identifier.py
scubatrace/joern.py
scubatrace/language.py
scubatrace/parser.py
scubatrace/project.py
scubatrace/statement.py
scubatrace/cpp/file.py
scubatrace/cpp/function.py
scubatrace/cpp/identifier.py
scubatrace/cpp/language.py
scubatrace/cpp/parser.py
scubatrace/cpp/project.py
scubatrace/cpp/statement.py
scubatrace/csharp/file.py
scubatrace/csharp/function.py
scubatrace/csharp/identifier.py
scubatrace/csharp/language.py
scubatrace/csharp/parser.py
scubatrace/csharp/project.py
scubatrace/csharp/statement.py
scubatrace/go/file.py
scubatrace/go/function.py
scubatrace/go/identifier.py
scubatrace/go/language.py
scubatrace/go/parser.py
scubatrace/go/project.py
scubatrace/go/statement.py
scubatrace/java/file.py
scubatrace/java/function.py
scubatrace/java/identifier.py
scubatrace/java/language.py
scubatrace/java/parser.py
scubatrace/java/project.py
scubatrace/java/statement.py
scubatrace/javascript/file.py
scubatrace/javascript/function.py
scubatrace/javascript/identifier.py
scubatrace/javascript/language.py
scubatrace/javascript/parser.py
scubatrace/javascript/project.py
scubatrace/javascript/statement.py
scubatrace/php/file.py
scubatrace/php/function.py
scubatrace/php/identifier.py
scubatrace/php/language.py
scubatrace/php/parser.py
scubatrace/php/project.py
scubatrace/php/statement.py
scubatrace/python/file.py
scubatrace/python/function.py
scubatrace/python/identifier.py
scubatrace/python/language.py
scubatrace/python/parser.py
scubatrace/python/project.py
scubatrace/python/statement.py
scubatrace/ruby/file.py
scubatrace/ruby/function.py
scubatrace/ruby/identifier.py
scubatrace/ruby/language.py
scubatrace/ruby/parser.py
scubatrace/ruby/project.py
scubatrace/ruby/statement.py
scubatrace/rust/file.py
scubatrace/rust/function.py
scubatrace/rust/identifier.py
scubatrace/rust/language.py
scubatrace/rust/parser.py
scubatrace/rust/project.py
scubatrace-1.0.5.dist-info/licenses/LICENSE
scubatrace-1.0.5.dist-info/METADATA
scubatrace-1.0.5.dist-info/WHEEL
scubatrace-1.0.5.dist-info/top_level.txt
scubatrace-1.0.5.dist-info/RECORD
