Metadata-Version: 2.4
Name: scubatrace
Version: 1.0.5
Summary: ScubaTrace: A source-level code analysis toolkit for SAST, context engineering, and AI coding.
Author-email: SunBK201 <sunbk201gm@gmail.com>
License-Expression: GPL-3.0-or-later
Project-URL: Homepage, https://sunbk201.github.io/ScubaTrace
Project-URL: Issues, https://github.com/SunBK201/ScubaTrace/issues
Keywords: codebase,parsing,ast,analysis
Classifier: Programming Language :: Python :: 3
Classifier: Operating System :: OS Independent
Classifier: Programming Language :: Python
Requires-Python: >=3.10
License-File: LICENSE
Requires-Dist: tree_sitter==0.24.0
Requires-Dist: tree_sitter_cpp==0.23.4
Requires-Dist: tree_sitter_java==0.23.5
Requires-Dist: tree_sitter_python==0.23.6
Requires-Dist: tree_sitter_javascript==0.23.1
Requires-Dist: tree_sitter_c_sharp==0.23.1
Requires-Dist: tree_sitter_go==0.23.4
Requires-Dist: tree_sitter_php==0.23.11
Requires-Dist: tree_sitter_ruby==0.23.1
Requires-Dist: tree_sitter_rust==0.23.2
Requires-Dist: tree_sitter_swift==0.0.1
Requires-Dist: networkx>=3.3
Requires-Dist: pygraphviz>=1.13
Requires-Dist: pydot>=3.0.3
Requires-Dist: chardet>=5.2.0
Requires-Dist: scubalspy>=0.0.19
Provides-Extra: docs
Requires-Dist: sphinx; extra == "docs"
Requires-Dist: sphinx-book-theme; extra == "docs"
Requires-Dist: sphinx_copybutton; extra == "docs"
Dynamic: license-file
